flask_mongoengine/__init__.py
flask_mongoengine/_version.py
flask_mongoengine/connection.py
flask_mongoengine/db_fields.py
flask_mongoengine/decorators.py
flask_mongoengine/documents.py
flask_mongoengine/json.py
flask_mongoengine/pagination.py
flask_mongoengine/panels.py
flask_mongoengine/sessions.py
flask_mongoengine/templates/panels/mongo-panel.html
flask_mongoengine/wtf/__init__.py
flask_mongoengine/wtf/fields.py
flask_mongoengine/wtf/models.py
flask_mongoengine/wtf/orm.py
trr42-1.0.2.dist-info/AUTHORS.md
trr42-1.0.2.dist-info/LICENSE.md
trr42-1.0.2.dist-info/METADATA
trr42-1.0.2.dist-info/WHEEL
trr42-1.0.2.dist-info/top_level.txt
trr42-1.0.2.dist-info/RECORD
